LICENSE
README.md
setup.py
Sylvac_V02/__init__.py
Sylvac_V02/main.py
Sylvac_V02.egg-info/PKG-INFO
Sylvac_V02.egg-info/SOURCES.txt
Sylvac_V02.egg-info/dependency_links.txt
Sylvac_V02.egg-info/top_level.txt