Metadata-Version: 2.1
Name: Sylvac-V02
Version: 0.0.0
Summary: Phần mềm kết nối với thiết bị đo DiaTest
Home-page: https://github.com/huynhquoc1990/Sylvac_V02.git
Author: Huynh-Quoc
Author-email: huynhquoc1990@gmail.com
License: MIT
Platform: UNKNOWN
License-File: LICENSE
